[
    {
        "numeroPedido": 2433,
        "emailUsuario": "jony@gmail.com",
        "idHamburguesa": 383,
        "fecha": "2023-06-07",
        "cantidad": 3,
        "imagen": "ImagenesDeLaVenta\/2023\/simplebigMacjony2023-06-08.jpg"
    },
    {
        "numeroPedido": 2344,
        "emailUsuario": "opera2@gmail.com",
        "idHamburguesa": 279,
        "fecha": "2023-06-08",
        "cantidad": 1,
        "imagen": "ImagenesDeLaVenta\/2023\/doblemacNificaopera22023-06-08.jpeg"
    },
    {
        "numeroPedido": 2565,
        "emailUsuario": "jonyalanoca@gmail.com",
        "idHamburguesa": 383,
        "fecha": "2023-06-08",
        "cantidad": 1,
        "imagen": "ImagenesDeLaVenta\/2023\/simplebigMacjonyalanoca2023-06-08.jpg"
    }
]